files_dal/__init__.py
files_dal-0.0.1.post1.dist-info/METADATA
files_dal-0.0.1.post1.dist-info/WHEEL
files_dal-0.0.1.post1.dist-info/entry_points.txt
files_dal-0.0.1.post1.dist-info/top_level.txt
files_dal-0.0.1.post1.dist-info/RECORD
